datamap/posmo_datamarket_sdk/__init__.py
datamap/posmo_datamarket_sdk/sdk.py
datamap_posmo_datamarket_sdk-1.0.0.dist-info/METADATA
datamap_posmo_datamarket_sdk-1.0.0.dist-info/WHEEL
datamap_posmo_datamarket_sdk-1.0.0.dist-info/licenses/LICENCE
datamap_posmo_datamarket_sdk-1.0.0.dist-info/RECORD
