Metadata-Version: 2.3
Name: datamap.posmo_datamarket_sdk
Version: 1.0.0
Summary: SDK for interacting with Posmo DataMarket API
Project-URL: Homepage, https://github.com/datamapio/datamarket-sdk
Project-URL: Issues, https://github.com/datamapio/datamarket-sdk/issues
Author-email: Datamap <contact@datamap.io>
License-File: LICENCE
Classifier: License :: OSI Approved :: MIT License
Classifier: Operating System :: OS Independent
Classifier: Programming Language :: Python :: 3
Requires-Python: >=3.8
Requires-Dist: requests>=2.20.0
